dynamodbgeo/DynamoDBManager.py
dynamodbgeo/GeoDataManager.py
dynamodbgeo/GeoDataManagerConfiguration.py
dynamodbgeo/__init__.py
dynamodbgeo/model/Covering.py
dynamodbgeo/model/DeleteItemInput.py
dynamodbgeo/model/GeoPoint.py
dynamodbgeo/model/GeoQueryInput.py
dynamodbgeo/model/GeohashRange.py
dynamodbgeo/model/GetPointInput.py
dynamodbgeo/model/PutPointInput.py
dynamodbgeo/model/QueryRadiusRequest.py
dynamodbgeo/model/QueryRectangleRequest.py
dynamodbgeo/model/UpdateItemInput.py
dynamodbgeo/model/__init__.py
dynamodbgeo/s2/S2Manager.py
dynamodbgeo/s2/S2Util.py
dynamodbgeo/s2/__init__.py
dynamodbgeo/util/GeoTableUtil.py
dynamodbgeo/util/__init__.py
tests/__init__.py
tests/test_create_table.py
tests/test_get_point.py
tests/test_put_point.py
tests/test_query_radius.py
tests/test_query_radius_sort.py
tests/test_query_rectangle.py
tests/vars.py
dynamodbgeo-0.0.3.dist-info/LICENSE
dynamodbgeo-0.0.3.dist-info/METADATA
dynamodbgeo-0.0.3.dist-info/WHEEL
dynamodbgeo-0.0.3.dist-info/top_level.txt
dynamodbgeo-0.0.3.dist-info/RECORD
