Metadata-Version: 2.1
Name: dynamodbgeo
Version: 0.0.3
Summary: A python port of awslabs/dynamodb-geo, for easier geospatial data manipulation and querying in DynamoDB
Home-page: https://github.com/Sigm0oid/dynamodb-geo.py
Author: Hamza Rhibi & Walid Sadallah
Author-email: elrhibihamzas@gmail.com
License: MIT
Platform: UNKNOWN
Classifier: License :: OSI Approved :: MIT License
Classifier: Programming Language :: Python :: 3
Classifier: Programming Language :: Python :: 3.7
